{
  "updated_at": "2026-02-24T10:13:44.320577+00:00",
  "updated_kst": "2026-02-24 19:13 KST",
  "summary": [],
  "market_strength": "",
  "sectors": [],
  "stocks": [],
  "news": [],
  "recommendations": [
    {
      "name": "HPSP",
      "grade": "A+",
      "timeframe": "중장기",
      "reason": "고압 어닐링 장비의 선도 공급업체, 반도체 공급망 핵심 조력자",
      "featured": true
    },
    {
      "name": "SK하이닉스",
      "grade": "A+",
      "timeframe": "중장기",
      "reason": "AI 성장의 직접 수혜 기업, 기술 리더십 기반의 높은 진입 장벽",
      "featured": false
    },
    {
      "name": "한화비전",
      "grade": "A0",
      "timeframe": "중장기",
      "reason": "거래대금 폭발 및 AI 카메라 테마 주도주",
      "featured": false
    },
    {
      "name": "온코닉테라퓨틱",
      "grade": "B+",
      "timeframe": "단기",
      "reason": "제약바이오 신고가 및 상한가 돌파, 수급 집중",
      "featured": false
    },
    {
      "name": "STX엔진",
      "grade": "B+",
      "timeframe": "중장기",
      "reason": "AI 데이터센터의 고밀도화에 따라 필수적인 발전 설비 및 UPS 시스템으로 사업 다각화 중, 글로벌 AI 전력 수요 구조적 투자 확대",
      "featured": false
    }
  ],
  "indices": {
    "kospi": {
      "price": 5970.0,
      "change": 161.0,
      "pct": 2.77,
      "pos": true
    },
    "kosdaq": {
      "price": 1165.0,
      "change": 11.0,
      "pct": 0.95,
      "pos": true
    },
    "sp500": {
      "price": 6838.0,
      "change": -24.0,
      "pct": -0.35,
      "pos": false
    },
    "nasdaq": {
      "price": 22627.0,
      "change": -55.0,
      "pct": -0.24,
      "pos": false
    },
    "usdkrw": {
      "price": 1442.2,
      "change": -1.3,
      "pct": -0.09,
      "pos": false
    },
    "us10y": {
      "price": 4.029,
      "change": -0.057,
      "pct": -1.4,
      "pos": false
    },
    "wti": {
      "price": 66.5,
      "change": 0.19,
      "pct": 0.29,
      "pos": true
    },
    "gold": {
      "price": 5194.0,
      "change": -11.0,
      "pct": -0.21,
      "pos": false
    }
  }
}